[
  {
    "column_name": "date",
    "generate_type": "product",
    "generate_data": [
      "2023/02/01",
      "2023/02/02",
      "2023/02/03",
      "2023/02/04",
      "2023/02/05",
      "2023/02/06",
      "2023/02/07",
      "2023/02/08",
      "2023/02/09",
      "2023/02/10"
    ]
  },
  {
    "column_name": "enddate",
    "linked_cname": "date",
    "generate_data": [
      "2023/02/15",
      "2023/02/06",
      "2023/02/14",
      "2023/02/28",
      "2023/03/04",
      "2023/02/27",
      "2023/02/20",
      "2023/03/07",
      "2023/02/19",
      "2023/03/04"
    ]
  },
  {
    "column_name": "datetime",
    "generate_type": "product",
    "generate_data": [
      "2023/02/25 00:00:00",
      "2023/02/25 01:00:00",
      "2023/02/25 02:00:00",
      "2023/02/25 03:00:00",
      "2023/02/25 04:00:00",
      "2023/02/25 05:00:00",
      "2023/02/25 06:00:00",
      "2023/02/25 07:00:00",
      "2023/02/25 08:00:00",
      "2023/02/25 09:00:00"
    ]
  },
  {
    "column_name": "enddatetime",
    "linked_cname": "datetime",
    "generate_data": [
      "2023/02/25 00:00:47",
      "2023/02/25 01:00:21",
      "2023/02/25 02:00:05",
      "2023/02/25 03:00:42",
      "2023/02/25 04:00:19",
      "2023/02/25 05:00:12",
      "2023/02/25 06:00:54",
      "2023/02/25 07:00:50",
      "2023/02/25 08:00:05",
      "2023/02/25 09:00:29"
    ]
  },
  {
    "column_name": "code",
    "generate_type": "random",
    "generate_data": [
      "a",
      "b",
      "c"
    ]
  },
  {
    "column_name": "value",
    "linked_cname": "code",
    "generate_data": [
      "A",
      "B",
      "C"
    ]
  },
  {
    "column_name": "code2",
    "generate_type": "product",
    "generate_data": [
      "11",
      "22",
      "33"
    ]
  },
  {
    "column_name": "value2",
    "linked_cname": "code2",
    "generate_data": [
      "one",
      "two",
      "three"
    ]
  }
]